proxenos/__init__.py
proxenos/__init__.pyc
proxenos/__main__.py
proxenos/cli.py
proxenos/cli.pyc
proxenos/config.py
proxenos/config.pyc
proxenos/node.py
proxenos/node.pyc
proxenos/node.pyi
proxenos/rendezvous.py
proxenos/rendezvous.pyc
proxenos/__pycache__/__init__.cpython-35.pyc
proxenos/__pycache__/__init__.cpython-36.pyc
proxenos/__pycache__/config.cpython-35.pyc
proxenos/__pycache__/node.cpython-35.pyc
proxenos/__pycache__/node.cpython-36.pyc
proxenos/__pycache__/rendezvous.cpython-35.pyc
proxenos/__pycache__/rendezvous.cpython-36.pyc
proxenos/mappers/__init__.py
proxenos/mappers/__init__.pyc
proxenos/mappers/base.py
proxenos/mappers/base.pyc
proxenos/mappers/consul.py
proxenos/mappers/consul.pyc
proxenos-0.0.3.dist-info/DESCRIPTION.rst
proxenos-0.0.3.dist-info/METADATA
proxenos-0.0.3.dist-info/RECORD
proxenos-0.0.3.dist-info/WHEEL
proxenos-0.0.3.dist-info/entry_points.txt
proxenos-0.0.3.dist-info/metadata.json
proxenos-0.0.3.dist-info/top_level.txt
