Metadata-Version: 2.0
Name: proxenos
Version: 0.0.3
Summary: proxenos: A rendezvous hashing and service routing toolkit.
Home-page: https://github.com/darvid/proxenos
Author: David Gidwani
Author-email: david.gidwani@gmail.com
License: UNKNOWN
Platform: UNKNOWN
Classifier: Development Status :: 2 - Pre-Alpha
Classifier: Environment :: Console
Classifier: Intended Audience :: Developers
Classifier: License :: OSI Approved :: MIT License
Classifier: Operating System :: MacOS
Classifier: Operating System :: Microsoft :: Windows
Classifier: Operating System :: POSIX :: Linux
Classifier: Operating System :: Unix
Classifier: Programming Language :: Python :: 2
Classifier: Programming Language :: Python :: 2.7
Classifier: Programming Language :: Python :: 3
Classifier: Programming Language :: Python :: 3.3
Classifier: Programming Language :: Python :: 3.4
Classifier: Programming Language :: Python :: 3.5
Classifier: Programming Language :: Python :: 3.6
Classifier: Programming Language :: Python :: Implementation :: CPython
Classifier: Programming Language :: Python :: Implementation :: PyPy
Classifier: Programming Language :: Python
Classifier: Topic :: Software Development :: Libraries :: Python Modules
Classifier: Topic :: Software Development :: Libraries
Classifier: Topic :: Utilities
Requires-Dist: attrs
Requires-Dist: consulate
Requires-Dist: netaddr
Requires-Dist: siphash
Requires-Dist: stevedore
Requires-Dist: typing; python_version<"3.5"
Requires-Dist: enum34; python_version=="2.7"
Provides-Extra: consul
Requires-Dist: consulate; extra == 'consul'
Provides-Extra: murmur
Requires-Dist: mmh3; extra == 'murmur'
